[
  {
    "title": "This Month in Rust GameDev #40 - November 2022 | Rust GameDev WG",
    "link": "https://gamedev.rs/news/040/"
  },
  {
    "title": "This Month in Rust GameDev #36 - July 2022 | Rust GameDev WG",
    "link": "https://gamedev.rs/news/036/"
  },
  {
    "title": "This Month in Rust GameDev #34 - May 2022 | Rust GameDev WG",
    "link": "https://gamedev.rs/news/034/"
  },
  {
    "title": "This Month in Rust GameDev #30 - January 2022 | Rust GameDev WG",
    "link": "https://gamedev.rs/news/030/"
  },
  {
    "title": "The year 2021 in Dimforge and our objectives for 2022 | Dimforge",
    "link": "https://dimforge.com/blog/2022/01/02/the-year-2021-in-dimforge/"
  },
  {
    "title": "This Month in Rust GameDev #27 - October 2021 | Rust GameDev WG",
    "link": "https://gamedev.rs/news/027/"
  },
  {
    "title": "This Month in Rust GameDev #25 - August 2021 | Rust GameDev WG",
    "link": "https://gamedev.rs/news/025/"
  },
  {
    "title": "This Month in Rust GameDev #23 - June 2021 | Rust GameDev WG",
    "link": "https://gamedev.rs/news/023/"
  },
  {
    "title": "This Month in Rust GameDev #22 - May 2021 | Rust GameDev WG",
    "link": "https://gamedev.rs/news/022/"
  },
  {
    "title": "This month in Dimforge \\#3 (November 2020) | Dimforge",
    "link": "https://www.dimforge.com/blog/2020/12/01/this-month-in-dimforge/"
  },
  {
    "title": "This month in Dimforge \\#2 (October 2020) | Dimforge",
    "link": "https://www.dimforge.com/blog/2020/11/01/this-month-in-dimforge/"
  },
  {
    "title": "This month in Dimforge \\#1 (September 2020) | Dimforge",
    "link": "https://www.dimforge.com/blog/2020/10/01/this-month-in-dimforge/"
  },
  {
    "title": "Announcing the Rapier physics engine | Dimforge",
    "link": "https://www.dimforge.com/blog/2020/08/25/announcing-the-rapier-physics-engine/"
  },
  {
    "title": "Rustsim becomes Dimforge | Dimforge",
    "link": "https://www.dimforge.com/blog/2020/08/18/rustsim-becomes-dimforge/"
  }
]