[
  {
    "date": "2024-07-24",
    "title": "Diesel Async 0.5 - Weiznich's Blog",
    "link": "https://blog.weiznich.de/blog/diesel-async-0-5/"
  },
  {
    "date": "2024-05-22",
    "title": "Towards fast `thread_local!` context",
    "link": "https://swatinem.de/blog/thread-local-context/"
  },
  {
    "date": "2024-04-24",
    "title": "Why SQLite Performance Tuning made Bencher 1200x Faster | Bencher - Continuous Benchmarking",
    "link": "https://bencher.dev/learn/engineering/sqlite-performance-tuning/"
  },
  {
    "date": "2024-04-03",
    "title": "Universal domain types",
    "link": "https://mmapped.blog/posts/25-domain-types.html"
  },
  {
    "date": "2024-04-03",
    "title": "Dioxus | An elegant GUI library for Rust",
    "link": "https://dioxuslabs.com/blog/release-050"
  },
  {
    "date": "2024-03-13",
    "title": "Problems around modelling an asynchronous API for database transaction in Rust - Weiznich's Blog",
    "link": "https://blog.weiznich.de/blog/async-transaction-problem/"
  },
  {
    "date": "2023-12-27",
    "title": "Web development in Rust",
    "link": "https://rust.code-maven.com/web"
  },
  {
    "date": "2023-11-01",
    "title": "Faster Rust Serialization",
    "link": "https://mo8it.com/blog/faster-rust-serialization/"
  },
  {
    "date": "2023-10-04",
    "title": "Divan: Fast and Simple Benchmarking for Rust · Nikolai Vazquez",
    "link": "https://nikolaivazquez.com/blog/divan/"
  },
  {
    "date": "2023-09-06",
    "title": "Diesel Async 0.4 - Weiznich's Blog",
    "link": "https://blog.weiznich.de/blog/diesel-async-0-4/"
  },
  {
    "date": "2023-08-16",
    "title": "Our latest adventures with bindgen  - Ferrous Systems",
    "link": "https://ferrous-systems.com/blog/bindgen/"
  },
  {
    "date": "2023-03-01",
    "title": "Dioxus | An elegant GUI library for Rust",
    "link": "https://dioxuslabs.com/blog/release-030/"
  },
  {
    "date": "2023-01-18",
    "title": "Displaying Images on ESP32 with Rust! - lily's thots",
    "link": "https://lilymara.xyz/posts/images-esp32/"
  },
  {
    "date": "2023-01-18",
    "title": "https://blaz.is/blog/post/we-dont-need-a-stable-abi/",
    "link": "https://blaz.is/blog/post/we-dont-need-a-stable-abi/"
  },
  {
    "date": "2022-12-28",
    "title": "Capture The IP — Or a tiny story about how to over-engineer a simple project for the sake of learning Rust and other things about web services and binaries | markentier.tech",
    "link": "https://markentier.tech/posts/2022/12/capture-the-ip/"
  },
  {
    "date": "2022-12-21",
    "title": "UI development in Rust | Raimundo Saona",
    "link": "https://saona-raimundo.github.io/2022/12/21/UI-development-in-Rust.html"
  },
  {
    "date": "2022-12-14",
    "title": "Dioxus | An elegant GUI library for Rust",
    "link": "https://dioxuslabs.com/blog/templates-diffing/"
  },
  {
    "date": "2022-09-28",
    "title": "Accessing Firebird With Diesel and Rust | by Luis Fernando Batels | Better Programming",
    "link": "https://betterprogramming.pub/diesel-firebird-en-a4d00e793e1d"
  },
  {
    "date": "2022-06-29",
    "title": "fetch_data - Rust",
    "link": "https://docs.rs/fetch-data/latest/fetch_data/"
  },
  {
    "date": "2022-03-16",
    "title": "Dioxus | An elegant GUI library for Rust",
    "link": "https://dioxuslabs.com/blog/release-020"
  },
  {
    "date": "2022-01-05",
    "title": "Dioxus | An elegant GUI library for Rust",
    "link": "https://dioxuslabs.com/blog/introducing-dioxus/"
  },
  {
    "date": "2021-10-13",
    "title": "Alexis Lozano",
    "link": "https://alexis-lozano.com/hexagonal-architecture-in-rust-6/"
  },
  {
    "date": "2021-06-16",
    "title": "Introducing cap-std, a capability-based version of the Rust standard library · sunfishcode's blog",
    "link": "https://blog.sunfishcode.online/introducing-cap-std/"
  },
  {
    "date": "2021-05-05",
    "title": "display_utils - Rust",
    "link": "https://docs.rs/display_utils"
  },
  {
    "date": "2021-04-14",
    "title": "dipa - Rust",
    "link": "https://docs.rs/dipa"
  },
  {
    "date": "2021-02-17",
    "title": "The XDG base directory specification and Rust",
    "link": "https://blog.liw.fi/posts/2021/02/14/xdg-base-dirs-rust/"
  },
  {
    "date": "2020-09-02",
    "title": "HTML forms, Databases, Integration tests | Luca Palmieri",
    "link": "https://www.lpalmieri.com/posts/2020-08-31-zero-to-production-3-5-html-forms-databases-integration-tests/"
  },
  {
    "date": "2020-08-25",
    "title": "Rust Embedded Working Group",
    "link": "https://rust-embedded.github.io/blog/newsletter-25/"
  },
  {
    "date": "2020-06-23",
    "title": "GitHub Action for binary crates installation · svartalf",
    "link": "https://svartalf.info/posts/2020-04-10-github-action-for-binary-crates-installation/"
  },
  {
    "date": "2020-06-02",
    "title": "kitsu's blog",
    "link": "https://kitsu.me/posts/2020_05_24_custom_types_in_diesel"
  },
  {
    "date": "2020-04-21",
    "title": "How I Reverse Engineered the LastPass CLI Tool · Michael-F-Bryan",
    "link": "http://adventures.michaelfbryan.com/posts/lastpass/"
  },
  {
    "date": "2018-05-01",
    "title": "An alias-based formulation of the borrow checker · baby steps",
    "link": "http://smallcultfollowing.com/babysteps/blog/2018/04/27/an-alias-based-formulation-of-the-borrow-checker/"
  },
  {
    "date": "2017-11-07",
    "title": "2008-non-exhaustive - The Rust RFC Book",
    "link": "https://rust-lang.github.io/rfcs/2008-non-exhaustive.html"
  },
  {
    "date": "2017-03-28",
    "title": "Diesel is a Safe, Extensible ORM and Query Builder for Rust",
    "link": "https://diesel.rs"
  },
  {
    "date": "2017-01-03",
    "title": "Elegant Library APIs in Rust - Pascal’s Scribbles",
    "link": "https://scribbles.pascalhertleif.de/elegant-apis-in-rust.html"
  },
  {
    "date": "2016-10-11",
    "title": "Diesel is a Safe, Extensible ORM and Query Builder for Rust",
    "link": "http://diesel.rs/"
  },
  {
    "date": "2015-11-30",
    "title": "Announcing Diesel — A Safe, Extensible ORM and Query Builder for Rust | by Sean Griffin | Medium",
    "link": "https://medium.com/@sgrif/announcing-diesel-a-safe-extensible-orm-and-query-builder-for-rust-fdf57966a16c"
  }
]