[
  {
    "date": "2022-03-02",
    "title": "Building a new graphics engine in Rust - Part 2 – Alex Dixon",
    "link": "https://www.polymonster.co.uk/blog/bulding-new-engine-in-rust-2"
  },
  {
    "date": "2021-07-21",
    "title": "Release of v0.9 and the Future of wgpu - gfx-rs nuts and bolts",
    "link": "https://gfx-rs.github.io/2021/07/16/release-0.9-future.html"
  },
  {
    "date": "2021-07-14",
    "title": "This Month in Rust GameDev #23 - June 2021 | Rust GameDev WG",
    "link": "https://gamedev.rs/news/023/"
  },
  {
    "date": "2021-06-16",
    "title": "This Month in Rust GameDev #22 - May 2021 | Rust GameDev WG",
    "link": "https://gamedev.rs/news/022/"
  },
  {
    "date": "2021-05-12",
    "title": "Shader translation benchmark on Dota2/Metal - gfx-rs nuts and bolts",
    "link": "https://gfx-rs.github.io/2021/05/09/dota2-msl-compilation.html"
  },
  {
    "date": "2021-05-12",
    "title": "This Month in Rust GameDev #21 - April 2021 | Rust GameDev WG",
    "link": "https://gamedev.rs/news/021/"
  },
  {
    "date": "2021-05-05",
    "title": "Release of v0.8 - gfx-rs nuts and bolts",
    "link": "https://gfx-rs.github.io/2021/04/30/release-0.8.html"
  },
  {
    "date": "2021-04-14",
    "title": "This Month in Rust GameDev #20 - March 2021 | Rust GameDev WG",
    "link": "https://gamedev.rs/news/020/"
  },
  {
    "date": "2021-02-03",
    "title": "Release of v0.7 - gfx-rs nuts and bolts",
    "link": "https://gfx-rs.github.io/2021/02/02/release-0.7.html"
  },
  {
    "date": "2020-11-25",
    "title": "FBSim: football-playing AI agents in Rust – Computer Wit",
    "link": "https://iantayler.com/2020/11/22/fbsim-football-playing-ai-agents-in-rust/"
  },
  {
    "date": "2020-11-18",
    "title": "The Big Picture - gfx-rs nuts and bolts",
    "link": "https://gfx-rs.github.io/2020/11/16/big-picture.html"
  },
  {
    "date": "2020-05-12",
    "title": "Wiki - WritingAWaylandCompositorInRust",
    "link": "https://wiki.alopex.li/WritingAWaylandCompositorInRust"
  },
  {
    "date": "2020-04-29",
    "title": "A Taste of WebGPU in Firefox - Mozilla Hacks - the Web developer blog",
    "link": "https://hacks.mozilla.org/2020/04/experimental-webgpu-in-firefox/"
  },
  {
    "date": "2020-04-21",
    "title": "wgpu-rs on the web - gfx-rs nuts and bolts",
    "link": "https://gfx-rs.github.io/2020/04/21/wgpu-web.html"
  },
  {
    "date": "2019-10-01",
    "title": "Project update - gfx-rs nuts and bolts",
    "link": "https://gfx-rs.github.io/2019/10/01/update.html"
  },
  {
    "date": "2019-08-27",
    "title": "Thoughts on Rust bloat | Raph Levien’s blog",
    "link": "https://raphlinus.github.io/rust/2019/08/21/rust-bloat.html"
  },
  {
    "date": "2019-07-16",
    "title": "Javelin project - gfx-rs nuts and bolts",
    "link": "https://gfx-rs.github.io/2019/07/13/javelin.html"
  },
  {
    "date": "2019-06-18",
    "title": "5 Year Anniversary - gfx-rs nuts and bolts",
    "link": "https://gfx-rs.github.io/2019/06/12/anniversary-5.html"
  },
  {
    "date": "2019-03-12",
    "title": "The rise of wgpu - gfx-rs nuts and bolts",
    "link": "https://gfx-rs.github.io/2019/03/06/wgpu.html"
  },
  {
    "date": "2019-01-01",
    "title": "This Year in Gfx-rs - 2018 - gfx-rs nuts and bolts",
    "link": "https://gfx-rs.github.io/2018/12/27/this-year.html"
  },
  {
    "date": "2018-10-30",
    "title": "Eight million pixels and counting\n– 2d graphics in Rust discussion - A look at GPU memory management",
    "link": "https://nical.github.io/posts/rust-2d-graphics-02.html"
  },
  {
    "date": "2018-09-04",
    "title": "RPCS3 and Dolphin on macOS using gfx-portability - gfx-rs nuts and bolts",
    "link": "https://gfx-rs.github.io/2018/09/03/rpcs3-dolphin.html"
  },
  {
    "date": "2018-08-14",
    "title": "GSoC 2018 - D3D11 backend for gfx-rs - gfx-rs nuts and bolts",
    "link": "https://gfx-rs.github.io/2018/08/14/gsoc.html"
  },
  {
    "date": "2018-01-16",
    "title": "#Rust2018 — Aimlessly Going Forward",
    "link": "https://aimlesslygoingforward.com/blog/2018/01/10/rust-2018/"
  },
  {
    "date": "2018-01-09",
    "title": "rust2018.md · GitHub",
    "link": "https://gist.github.com/est31/c063704716b6880fd74ce2ba11b11298"
  },
  {
    "date": "2018-01-02",
    "title": "This Year in Gfx-rs - 2017 - gfx-rs nuts and bolts",
    "link": "http://gfx-rs.github.io/2017/12/30/this-year.html"
  },
  {
    "date": "2017-07-25",
    "title": "We need to go lower - gfx-rs nuts and bolts",
    "link": "https://gfx-rs.github.io/2017/07/24/low-level.html"
  },
  {
    "date": "2017-03-14",
    "title": "Building a parallel ECS in Rust",
    "link": "https://kvark.github.io/ecs/rust/2017/03/08/specs.html"
  },
  {
    "date": "2016-12-27",
    "title": "This Year in Gfx-rs - 2016 - gfx-rs nuts and bolts",
    "link": "https://gfx-rs.github.io/2016/12/21/this-year.html"
  },
  {
    "date": "2016-12-20",
    "title": "These weeks in PlanetKit #5: bits and bobs – Jeff Parsons",
    "link": "https://jeffparsons.github.io/2016/11/18/twipk-5/"
  },
  {
    "date": "2016-09-20",
    "title": "Programming Model - gfx-rs nuts and bolts",
    "link": "http://gfx-rs.github.io/2016/09/14/programming-model.html"
  },
  {
    "date": "2016-02-08",
    "title": "This Week in Amethyst 3 | Amethyst",
    "link": "https://thisweekinamethyst.wordpress.com/2016/02/01/twia-3/"
  },
  {
    "date": "2016-01-25",
    "title": "Pipeline State Objects - gfx-rs nuts and bolts",
    "link": "http://gfx-rs.github.io/2016/01/22/pso.html"
  }
]