[
  {
    "date": "2023-04-26",
    "title": "3308-offset_of - The Rust RFC Book",
    "link": "https://rust-lang.github.io/rfcs/3308-offset_of.html"
  },
  {
    "date": "2022-09-14",
    "title": "You Can't Do That: Abstracting over Ownership in Rust with Higher-Rank Type Bounds. Or Can You? | Armin Ronacher's Thoughts and Writings",
    "link": "https://lucumr.pocoo.org/2022/9/11/abstracting-over-ownership/"
  },
  {
    "date": "2022-07-27",
    "title": "Aya: your tRusty eBPF companion - Deepfence",
    "link": "https://deepfence.io/aya-your-trusty-ebpf-companion/"
  }
]