[
  {
    "date": "2024-04-03",
    "title": "Programming ESP32 with Rust: OTA firmware update",
    "link": "https://quan.hoabinh.vn/post/2024/3/programming-esp32-with-rust-ota-firmware-update"
  },
  {
    "date": "2020-09-30",
    "title": "Optimization - Making Rust Code Go Brrrr",
    "link": "https://aspenuwu.me/posts/rust-optimization.html"
  },
  {
    "date": "2020-03-03",
    "title": "Cheap tricks for high-performance Rust - Pascal’s Scribbles",
    "link": "https://deterministic.space/high-performance-rust.html"
  }
]