[
  {
    "date": "2024-08-21",
    "title": "Arenas",
    "link": "https://donsz.nl/blog/arenas/"
  },
  {
    "date": "2023-10-25",
    "title": "Object Soup is Made of Indexes",
    "link": "https://jacko.io/object_soup.html"
  },
  {
    "date": "2023-05-10",
    "title": "Episode 1: Hello, World! - The Way of the Crab",
    "link": "https://wayofthecrab.com/episodes/001/"
  },
  {
    "date": "2021-03-17",
    "title": "Arenas in Rust - In Pursuit of Laziness",
    "link": "https://manishearth.github.io/blog/2021/03/15/arenas-in-rust/"
  }
]